andeng/__init__.py
andeng/main.py
andeng-0.1.0.dist-info/entry_points.txt
andeng-0.1.0.dist-info/METADATA
andeng-0.1.0.dist-info/WHEEL
andeng-0.1.0.dist-info/RECORD
